MANIFEST.in
README.rst
setup.py
rollbackcontext/__init__.py
rollbackcontext.egg-info/PKG-INFO
rollbackcontext.egg-info/SOURCES.txt
rollbackcontext.egg-info/dependency_links.txt
rollbackcontext.egg-info/top_level.txt
rollbackcontext.egg-info/zip-safe