Metadata-Version: 1.1
Name: rollbackcontext
Version: 0.1-2
Summary: A context manager to do rollbacks automatically
Home-page: https://github.com/edwardbadboy/rollbackcontext
Author: Zhou Zheng Sheng
Author-email: zhshzhou@linux.vnet.ibm.com
License: LGPL2+
Keywords: rollback context manager
Platform: UNKNOWN
Classifier: Development Status :: 3 - Alpha
Classifier: Intended Audience :: Developers
Classifier: License :: OSI Approved :: GNU Lesser General Public License v2 or later (LGPLv2+)
Classifier: Programming Language :: Python :: 2.7
Classifier: Topic :: Software Development :: Libraries :: Python Modules
